gol_voos/__init__.py
gol_voos/dates.py
gol_voos/gol.py
gol_voos/html_scraper.py
gol_voos/util.py
gol_voos-0.0.2.dist-info/METADATA
gol_voos-0.0.2.dist-info/WHEEL
gol_voos-0.0.2.dist-info/licenses/LICENSE
gol_voos-0.0.2.dist-info/RECORD
