Metadata-Version: 2.1
Name: gol_voos
Version: 0.0.2
Summary: Scraping de dados de voo da empresa Gol utilizando selenium
Project-URL: Homepage, https://github.com/ricardostange/gol-voos
Project-URL: Bug Tracker, https://github.com/ricardostange/gol-voos/issues
Author-email: ricks <ricstange@gmail.com>
License-File: LICENSE
Classifier: License :: OSI Approved :: MIT License
Classifier: Operating System :: OS Independent
Classifier: Programming Language :: Python :: 3
Requires-Python: >=3.7
